liteutils/__init__.py
liteutils/_arxiv/__init__.py
liteutils/_arxiv/_arxiv_extraction.py
liteutils/_arxiv/_arxiv_latex.py
liteutils/_arxiv/_arxiv_read.py
liteutils/_pdf_to_image/__init__.py
liteutils/_pdf_to_image/main.py
liteutils/_pdf_to_image/outpu.png
liteutils/_pymupdf/__init__.py
liteutils/_reader/__init__.py
liteutils/_reader/all_files_reader.py
liteutils/common.py
liteutils-0.0.30.dist-info/METADATA
liteutils-0.0.30.dist-info/WHEEL
liteutils-0.0.30.dist-info/RECORD
